drf_apischema/__init__.py
drf_apischema/core.py
drf_apischema/decorator.py
drf_apischema/helpers.py
drf_apischema/locale/zh_Hans/LC_MESSAGES/django.po
drf_apischema/py.typed
drf_apischema/request.py
drf_apischema/response.py
drf_apischema/scalar/__init__.py
drf_apischema/scalar/apps.py
drf_apischema/scalar/get_filter_parameters.py
drf_apischema/scalar/templates/drf_apischema/scalar.html
drf_apischema/scalar/views.py
drf_apischema/settings.py
drf_apischema/urls.py
drf_apischema/utils.py
drf_apischema-0.3.5.dist-info/WHEEL
drf_apischema-0.3.5.dist-info/METADATA
drf_apischema-0.3.5.dist-info/RECORD
