Metadata-Version: 2.3
Name: drf-apischema
Version: 0.3.5
Summary: API schema generator and validator for Django REST framework
Keywords: drf,django,django-rest-framework,schema,swagger,openapi,documentation,drf-spectacular,drf-apischema
License: BSD 3-Clause License
Classifier: Framework :: Django
Classifier: Programming Language :: Python
Classifier: Programming Language :: Python :: 3
Classifier: Programming Language :: Python :: 3.12
Classifier: Programming Language :: Python :: 3.13
Classifier: Programming Language :: Python :: 3.14
Requires-Dist: django
Requires-Dist: django-restframework
Requires-Dist: rich
Requires-Dist: sqlparser
Requires-Dist: drf-spectacular
Requires-Python: >=3.12
Project-URL: Repository, https://github.com/hmeqo/drf-apischema.git
Project-URL: Issues, https://github.com/hmeqo/drf-apischema/issues
